{
	"editors": [
		{
			"type": "method",
			"id": 2147483638,
			"codeDescriptor": {
				"type": 1,
				"methodName": "Matrix_Print_2023_ORDA"
			}
		},
		{
			"type": "explorer"
		},
		{
			"type": "method",
			"id": 2147483641,
			"codeDescriptor": {
				"type": 1,
				"methodName": "Matrix_Print_2023"
			}
		},
		{
			"type": "method",
			"id": 2147483636,
			"codeDescriptor": {
				"type": 5,
				"databaseMethod": 1
			}
		},
		{
			"type": "method",
			"id": 2147483640,
			"codeDescriptor": {
				"type": 1,
				"methodName": "Matrix_Print_2023_Data"
			}
		},
		{
			"type": "method",
			"id": 2147483635,
			"codeDescriptor": {
				"type": 3,
				"formName": "Demo",
				"methodPath": "/SOURCES/Forms/Demo/method.4dm"
			}
		},
		{
			"type": "method",
			"id": 2147483647,
			"codeDescriptor": {
				"type": 1,
				"methodName": "00_OpenForm"
			}
		},
		{
			"type": "method",
			"id": 2147483634,
			"codeDescriptor": {
				"type": 2,
				"formName": "Demo",
				"objectName": "btn_CreateData_obj",
				"methodPath": "/SOURCES/Forms/Demo/ObjectMethods/btn_CreateData_obj.4dm"
			}
		},
		{
			"type": "form",
			"id": 514,
			"formName": "Demo"
		},
		{
			"type": "method",
			"id": 2147483631,
			"codeDescriptor": {
				"type": 2,
				"formName": "Demo",
				"objectName": "btn_DeleteData_obj",
				"methodPath": "/SOURCES/Forms/Demo/ObjectMethods/btn_DeleteData_obj.4dm"
			}
		},
		{
			"type": "method",
			"id": 2147483633,
			"codeDescriptor": {
				"type": 2,
				"formName": "Demo",
				"objectName": "Button1",
				"methodPath": "/SOURCES/Forms/Demo/ObjectMethods/btn_Print_wData_obj.4dm"
			}
		},
		{
			"type": "method",
			"id": 2147483632,
			"codeDescriptor": {
				"type": 2,
				"formName": "Demo",
				"objectName": "Button2",
				"methodPath": "/SOURCES/Forms/Demo/ObjectMethods/btn_Print_wCollection_obj.4dm"
			}
		},
		{
			"type": "toolbox"
		}
	]
}